{
    "tweets": [
        {
            "id": 1433895323219345410,
            "text": "Acer Chromebook 314 CB314-1H - Ordenador Portátil 14\" Full HD, Laptop (Intel Celeron N4020, 4GB RAM, 32GB eMMc, Int… https://t.co/e9suLqySKE",
            "created_at": "2021-09-03 20:51:00",
            "retweet_count": 0,
            "favorite_count": 0,
            "lang": "es",
            "geo": null,
            "coordinates": null,
            "mention": [],
            "label": "",
            "note": {},
            "user_id": 3407382137,
            "text_translation": ""
        },
        {
            "id": 1433817561016111111,
            "text": "Acer Chromebook 314 CB314-1H - Ordenador Portátil 14\" Full HD, Laptop (Intel Celeron N4020, 4GB RAM, 32GB eMMc, Int… https://t.co/MvICUrVD1c",
            "created_at": "2021-09-03 15:42:00",
            "retweet_count": 0,
            "favorite_count": 0,
            "lang": "es",
            "geo": null,
            "coordinates": null,
            "mention": [],
            "label": "",
            "note": {},
            "user_id": 3407382137,
            "text_translation": ""
        },
        {
            "id": 1433805753001910272,
            "text": "Aver Chromebook 314 , ideale per lo studio\n139 euro di sconto!!!\nAcquista ora!!!\nhttps://t.co/v6WY05kMWK\n#acer… https://t.co/nEl0r14MwT",
            "created_at": "2021-09-03 14:55:04",
            "retweet_count": 0,
            "favorite_count": 0,
            "lang": "it",
            "geo": null,
            "coordinates": null,
            "mention": [],
            "label": "",
            "note": {},
            "user_id": 2563342861,
            "text_translation": ""
        },
        {
            "id": 1433756699375149058,
            "text": "Aver Chromebook 314 , ideale per lo studio\n139 euro di sconto!!!\nhttps://t.co/RRJHxmFgHF\n\n#acer #WhatsApp #google #BackToSchool",
            "created_at": "2021-09-03 11:40:09",
            "retweet_count": 0,
            "favorite_count": 0,
            "lang": "it",
            "geo": null,
            "coordinates": null,
            "mention": [],
            "label": "",
            "note": {},
            "user_id": 1458560282,
            "text_translation": ""
        },
        {
            "id": 1433746341620961280,
            "text": "Acer Chromebook 314 CB314-1H - Ordenador Portátil 14\" Full HD, Laptop (Intel Celeron N4020, 4GB RAM, 32GB eMMc, Int… https://t.co/70JPBfkXrS",
            "created_at": "2021-09-03 10:59:00",
            "retweet_count": 0,
            "favorite_count": 0,
            "lang": "es",
            "geo": null,
            "coordinates": null,
            "mention": [],
            "label": "",
            "note": {},
            "user_id": 3407382137,
            "text_translation": ""
        },
        {
            "id": 1433695957359677448,
            "text": "PC Portable 14\" Acer Chromebook 314 - N4020, 4 Go de Ram, 64 Go de mémoire flash, Clavier Qwertz https://t.co/nr96czGXZJ",
            "created_at": "2021-09-03 07:38:47",
            "retweet_count": 0,
            "favorite_count": 0,
            "lang": "fr",
            "geo": null,
            "coordinates": null,
            "mention": [],
            "label": "",
            "note": {},
            "user_id": 786512340464263168,
            "text_translation": ""
        },
        {
            "id": 1433670089174175744,
            "text": "Acer Chromebook 314 CB314-1H - Ordenador Portátil 14\" Full HD, Laptop (Intel Celeron N4020, 4GB RAM, 32GB eMMc, Int… https://t.co/nsnyGOVU13",
            "created_at": "2021-09-03 05:56:00",
            "retweet_count": 0,
            "favorite_count": 0,
            "lang": "es",
            "geo": null,
            "coordinates": null,
            "mention": [],
            "label": "",
            "note": {},
            "user_id": 3407382137,
            "text_translation": ""
        }
    ]
}