{
    "tweets": [
        {
            "id": 1427995393292374022,
            "text": "Win a Gigabyte AERO 15 OLED Laptop thanks to NVIDIA GeForce AU! Don't miss out, ends Saturday 28 Aug! -… https://t.co/jwsfKdIDUg",
            "created_at": "2021-08-18 14:06:47",
            "retweet_count": 0,
            "favorite_count": 0,
            "lang": "en",
            "geo": null,
            "coordinates": null,
            "mention": [],
            "label": "",
            "note": {},
            "user_id": 552455067,
            "text_translation": ""
        },
        {
            "id": 1427918838033756167,
            "text": "Check this giveaway of a GIGABYTE AERO 15 XC notebook!\n👉 https://t.co/Kedvcm5eLd\n👉 https://t.co/Pg8JxRJgmv",
            "created_at": "2021-08-18 09:02:35",
            "retweet_count": 0,
            "favorite_count": 0,
            "lang": "en",
            "geo": null,
            "coordinates": null,
            "mention": [],
            "label": "",
            "note": {},
            "user_id": 1002924536407429125,
            "text_translation": ""
        }
    ]
}