{
    "tweets": [
        {
            "id": 1353126328917090304,
            "text": "ASUS TUF Gaming A15 FA506II-BQ029 \n15.6\" FullHD (Ryzen 7 4800H, 16 GB RAM, 1TB SSD, GeForce GTX1650Ti 4 GB GDDR6, S\u2026 https://t.co/Felif3JDcv",
            "created_at": "2021-01-23 23:43:51",
            "retweet_count": 0,
            "favorite_count": 0,
            "lang": "und",
            "geo": null,
            "coordinates": null,
            "mention": [],
            "label": "",
            "user_id": 1529240180
        },
        {
            "id": 1353126285971697664,
            "text": "ASUS TUF Gaming A15 FA506II-BQ029 \n15.6\" FullHD (Ryzen 7 4800H, 16 GB RAM, 1TB SSD, GeForce GTX1650Ti 4 GB GDDR6, S\u2026 https://t.co/dLzt8XNtLC",
            "created_at": "2021-01-23 23:43:41",
            "retweet_count": 0,
            "favorite_count": 0,
            "lang": "und",
            "geo": null,
            "coordinates": null,
            "mention": [],
            "label": "",
            "user_id": 1238185396359630848
        },
        {
            "id": 1353126239427506176,
            "text": "ASUS TUF Gaming A15 FA506II-BQ029 \n15.6\" FullHD (Ryzen 7 4800H, 16 GB RAM, 1TB SSD, GeForce GTX1650Ti 4 GB GDDR6, S\u2026 https://t.co/Kytxh75NQc",
            "created_at": "2021-01-23 23:43:30",
            "retweet_count": 0,
            "favorite_count": 0,
            "lang": "und",
            "geo": null,
            "coordinates": null,
            "mention": [],
            "label": "",
            "user_id": 282881077
        },
        {
            "id": 1353050996260417539,
            "text": "@springsa93 \u0627\u0648\u0646 X509JB \u062e\u0648\u0628\u0647. \u0645\u0646 \u0627\u06cc\u0646 \u0645\u062f\u0644 \u0631\u0648 Asus TUF Gaming A15 FX506LI \u067e\u06cc\u0634\u0646\u0647\u0627\u062f \u0645\u06cc\u062f\u0645 \u062a\u0648 \u0647\u0645\u0648\u0646 \u0631\u0646\u062c \u0642\u06cc\u0645\u062a\u06cc\u0647 \u062a\u0642\u0631\u06cc\u0628\u0627 \u062f\u0631 \u0639\u0648\u2026 https://t.co/kPrn6fTTsb",
            "created_at": "2021-01-23 18:44:30",
            "retweet_count": 0,
            "favorite_count": 0,
            "lang": "fa",
            "geo": null,
            "coordinates": null,
            "mention": [],
            "label": "",
            "user_id": 2690397534
        },
        {
            "id": 1352995060007235584,
            "text": "ASUS TUF Gaming A15 Gaming Laptop, 15.6\u201d 144Hz Full HD BUY NOW https://t.co/I7dhJDGf4c https://t.co/tu53t1vivQ",
            "created_at": "2021-01-23 15:02:14",
            "retweet_count": 0,
            "favorite_count": 0,
            "lang": "en",
            "geo": null,
            "coordinates": null,
            "mention": [],
            "label": "",
            "user_id": 1352956154494783494
        },
        {
            "id": 1352946238052839429,
            "text": "\ud83c\udf38\u30b2\u30fc\u30df\u30f3\u30b0\u30ce\u30fc\u30c8\u30d1\u30bd\u30b3\u30f3\ud83c\udf38\n\nASUS \u30b2\u30fc\u30df\u30f3\u30b0\u30ce\u30fc\u30c8\u30d1\u30bd\u30b3\u30f3 TUF Gaming A15 FA506IV(AMD Ryzen 9 4900H/16GB\u30fbSSD 512GB/RTX 2060/1,920\u00d71,080\u30c9\u30c3\u30c8 (\u2026 https://t.co/y5PYAxHamk",
            "created_at": "2021-01-23 11:48:14",
            "retweet_count": 0,
            "favorite_count": 0,
            "lang": "ja",
            "geo": null,
            "coordinates": null,
            "mention": [],
            "label": "",
            "user_id": 1282168309052399617
        },
        {
            "id": 1352856603163123718,
            "text": "ASUS Updates TUF Gaming A15 &amp; A17, Adds Ryzen 5000 &amp; GeForce RTX 30 Series\u00a0Hardware https://t.co/fPUHT9UECa",
            "created_at": "2021-01-23 05:52:03",
            "retweet_count": 0,
            "favorite_count": 0,
            "lang": "en",
            "geo": null,
            "coordinates": null,
            "mention": [],
            "label": "",
            "user_id": 1352684979789189120
        },
        {
            "id": 1352846142028054528,
            "text": "ASUSTek \u306e ASUS \u30b2\u30fc\u30df\u30f3\u30b0\u30ce\u30fc\u30c8\u30d1\u30bd\u30b3\u30f3TUF Gaming A15 FA506IH (Ryzen 7 4800H / GTX 1650 / 16GB\u30fbSSD 512GB / 15.6\u30a4\u30f3\u30c1 / \u30d5\u30ebHD(1920\u2026 https://t.co/LAEmqhPh94",
            "created_at": "2021-01-23 05:10:29",
            "retweet_count": 0,
            "favorite_count": 1,
            "lang": "ja",
            "geo": null,
            "coordinates": null,
            "mention": [],
            "label": "",
            "user_id": 1314307247573409792
        },
        {
            "id": 1352817883701645314,
            "text": "@honeniwatori \u3042\u30fc\u3061\u3087\u3063\u3068\u5f85\u3063\u3066\u4e0b\u3055\u3044\u3001\u305d\u308c\u306f\u5148\u306b\u4f3a\u3044\u305f\u304b\u3063\u305f\n\u3067\u3057\u305f\u3089\u3053\u3061\u3089\u3067\u3069\u3046\u3067\u3057\u3087\u3046\u304b\nCiv6\u63a8\u5968\u30b9\u30da\u30c3\u30af\u306b\u8fd1\u3044\u3082\u306e\u306b\u306a\u308a\u307e\u3059\n\u2192 ASUS TUF Gaming A15\nhttps://t.co/WuZM2w7rkJ",
            "created_at": "2021-01-23 03:18:12",
            "retweet_count": 0,
            "favorite_count": 0,
            "lang": "ja",
            "geo": null,
            "coordinates": null,
            "mention": [],
            "label": "",
            "user_id": 892697019814264832
        },
        {
            "id": 1352814579814854656,
            "text": "#\u304a\u524d\u3089\u306ePC\u30b9\u30da\u30c3\u30af\u6652\u3057\u3066\u3044\u3051\nASUS TUF Gaming A15 FA506II-R5G1650TYP\nM/B\uff1aASUSTek FA506II\nCPU\uff1aAMD Ryzen5 4600H(6\u30b3\u30a212\u30b9\u30ec\u30c3\u30c9\u30013.0GHz)\u2026 https://t.co/yHBwQde85L",
            "created_at": "2021-01-23 03:05:04",
            "retweet_count": 0,
            "favorite_count": 3,
            "lang": "ja",
            "geo": null,
            "coordinates": null,
            "mention": [],
            "label": "",
            "user_id": 1266783293858385925
        },
        {
            "id": 1352810464174960640,
            "text": "RT @ASUSJapan: \u30df\u30ea\u30bf\u30ea\u30fc\u30b0\u30ec\u30fc\u30c9\u306e\u30bf\u30d5\u306a\u30b2\u30fc\u30df\u30f3\u30b0\u30ce\u30fc\u30c8PC\u300cTUF Gaming A15/A17\u300d\u304c\u65b0\u767b\u5834\ud83c\udf89\n\n\u52dd\u5229\u3092\u63b4\u3080\u3001\u7a76\u6975\u306e\u30bf\u30d5\u30dc\u30c7\u30a3\u3002\n\u6700\u5927\u30677nm\u30d7\u30ed\u30bb\u30b9CPU AMD Ryzen\u2122 7 4800H\u3001GTX 1660 Ti\u3092\u642d\u8f09\u3057\u305f\u30e2\u30c7\u30eb\u3092\u3054\u7528\u610f\u3002\u2026",
            "created_at": "2021-01-23 02:48:43",
            "retweet_count": 71,
            "favorite_count": 0,
            "lang": "ja",
            "geo": null,
            "coordinates": null,
            "mention": [],
            "label": "",
            "user_id": 1266783293858385925
        },
        {
            "id": 1352770622464516096,
            "text": "@HardwareUnboxed @JarrodsTech @kitgurupress this time at least Asus pointes out a 90w tdp for the RTX 3070 from the\u2026 https://t.co/CWcoVteY1o",
            "created_at": "2021-01-23 00:10:24",
            "retweet_count": 0,
            "favorite_count": 0,
            "lang": "en",
            "geo": null,
            "coordinates": null,
            "mention": [],
            "label": "",
            "user_id": 1178646551004110848
        }
    ]
}