{
    "tweets": [
        {
            "id": 1413278226382610432,
            "text": " i would like to purchase lg wing tempered glass  but it was showing that sold out  when will it be in stock",
            "created_at": "2021-07-08 23:26:01",
            "retweet_count": 0,
            "favorite_count": 0,
            "lang": "en",
            "geo": null,
            "coordinates": null,
            "mention": [],
            "label": "",
            "user_id": 1409413251838791682,
            "text_translation": ""
        },
        {
            "id": 1413258307637293058,
            "text": "Screen Protector Clear Hydrogel Soft Film For LG Wing G8x ThinQ V20 G9 k51 Lot ebay cellphonesandaccessories LOFbNZrWJ3",
            "created_at": "2021-07-08 22:06:52",
            "retweet_count": 0,
            "favorite_count": 0,
            "lang": "en",
            "geo": null,
            "coordinates": null,
            "mention": [
                "Screen"
            ],
            "label": "",
            "user_id": 1224349999841984512,
            "text_translation": ""
        },
        {
            "id": 1413256478383820801,
            "text": "RT  when jibeoms name appeared as one of bomins friends in LG Wing CF  yes bobeom together forever uB7zdpl",
            "created_at": "2021-07-08 21:59:36",
            "retweet_count": 56,
            "favorite_count": 0,
            "lang": "en",
            "geo": null,
            "coordinates": null,
            "mention": [],
            "label": "",
            "user_id": 1014618591872847876,
            "text_translation": ""
        },
        {
            "id": 1413249665013895169,
            "text": "      Kg was a loser that never could get out of the fir 44LpJbphGp",
            "created_at": "2021-07-08 21:32:31",
            "retweet_count": 0,
            "favorite_count": 0,
            "lang": "en",
            "geo": null,
            "coordinates": null,
            "mention": [],
            "label": "",
            "user_id": 27146733,
            "text_translation": ""
        },
        {
            "id": 1413248256889475079,
            "text": "RT  when jibeoms name appeared as one of bomins friends in LG Wing CF  yes bobeom together forever uB7zdpl",
            "created_at": "2021-07-08 21:26:55",
            "retweet_count": 56,
            "favorite_count": 0,
            "lang": "en",
            "geo": null,
            "coordinates": null,
            "mention": [],
            "label": "",
            "user_id": 1347185068050161664,
            "text_translation": ""
        },
        {
            "id": 1413154000753414146,
            "text": "RT  when jibeoms name appeared as one of bomins friends in LG Wing CF  yes bobeom together forever uB7zdpl",
            "created_at": "2021-07-08 15:12:23",
            "retweet_count": 56,
            "favorite_count": 0,
            "lang": "en",
            "geo": null,
            "coordinates": null,
            "mention": [],
            "label": "",
            "user_id": 1191340200351260672,
            "text_translation": ""
        },
        {
            "id": 1413153007961743366,
            "text": " iPhone4iPhone5iPhone6iPhoneXiPhoneXRP40ProBlackShark3One Plus 8TLG WINGMi10ultraP20Pro",
            "created_at": "2021-07-08 15:08:26",
            "retweet_count": 0,
            "favorite_count": 2,
            "lang": "en",
            "geo": null,
            "coordinates": null,
            "mention": [],
            "label": "",
            "user_id": 1392968870210674689,
            "text_translation": ""
        },
        {
            "id": 1413140001559171078,
            "text": " can the lg wing be used in English if I bought the Korean model",
            "created_at": "2021-07-08 14:16:45",
            "retweet_count": 0,
            "favorite_count": 0,
            "lang": "en",
            "geo": null,
            "coordinates": null,
            "mention": [],
            "label": "",
            "user_id": 395612258,
            "text_translation": ""
        },
        {
            "id": 1413132474020810752,
            "text": "RT  when jibeoms name appeared as one of bomins friends in LG Wing CF  yes bobeom together forever uB7zdpl",
            "created_at": "2021-07-08 13:46:51",
            "retweet_count": 56,
            "favorite_count": 0,
            "lang": "en",
            "geo": null,
            "coordinates": null,
            "mention": [],
            "label": "",
            "user_id": 894493663794835456,
            "text_translation": ""
        },
        {
            "id": 1413127308165074947,
            "text": "RT  when jibeoms name appeared as one of bomins friends in LG Wing CF  yes bobeom together forever uB7zdpl",
            "created_at": "2021-07-08 13:26:19",
            "retweet_count": 56,
            "favorite_count": 0,
            "lang": "en",
            "geo": null,
            "coordinates": null,
            "mention": [],
            "label": "",
            "user_id": 1030264866840309760,
            "text_translation": ""
        },
        {
            "id": 1413113955698941953,
            "text": "RT  when jibeoms name appeared as one of bomins friends in LG Wing CF  yes bobeom together forever uB7zdpl",
            "created_at": "2021-07-08 12:33:16",
            "retweet_count": 56,
            "favorite_count": 0,
            "lang": "en",
            "geo": null,
            "coordinates": null,
            "mention": [],
            "label": "",
            "user_id": 4655299694,
            "text_translation": ""
        },
        {
            "id": 1413083031120715778,
            "text": "RT  when jibeoms name appeared as one of bomins friends in LG Wing CF  yes bobeom together forever uB7zdpl",
            "created_at": "2021-07-08 10:30:23",
            "retweet_count": 56,
            "favorite_count": 0,
            "lang": "en",
            "geo": null,
            "coordinates": null,
            "mention": [],
            "label": "",
            "user_id": 1075561026869850112,
            "text_translation": ""
        },
        {
            "id": 1413068623468392452,
            "text": "RT  when jibeoms name appeared as one of bomins friends in LG Wing CF  yes bobeom together forever uB7zdpl",
            "created_at": "2021-07-08 09:33:08",
            "retweet_count": 56,
            "favorite_count": 0,
            "lang": "en",
            "geo": null,
            "coordinates": null,
            "mention": [],
            "label": "",
            "user_id": 1163660992904957952,
            "text_translation": ""
        },
        {
            "id": 1413062801053024258,
            "text": "RT  when jibeoms name appeared as one of bomins friends in LG Wing CF  yes bobeom together forever uB7zdpl",
            "created_at": "2021-07-08 09:09:59",
            "retweet_count": 56,
            "favorite_count": 0,
            "lang": "en",
            "geo": null,
            "coordinates": null,
            "mention": [],
            "label": "",
            "user_id": 1119961016744337408,
            "text_translation": ""
        },
        {
            "id": 1413043742668320769,
            "text": "RT  when jibeoms name appeared as one of bomins friends in LG Wing CF  yes bobeom together forever uB7zdpl",
            "created_at": "2021-07-08 07:54:15",
            "retweet_count": 56,
            "favorite_count": 0,
            "lang": "en",
            "geo": null,
            "coordinates": null,
            "mention": [],
            "label": "",
            "user_id": 1166685446685855744,
            "text_translation": ""
        },
        {
            "id": 1413040771956019208,
            "text": "RT  when jibeoms name appeared as one of bomins friends in LG Wing CF  yes bobeom together forever uB7zdpl",
            "created_at": "2021-07-08 07:42:27",
            "retweet_count": 56,
            "favorite_count": 0,
            "lang": "en",
            "geo": null,
            "coordinates": null,
            "mention": [],
            "label": "",
            "user_id": 861245208612052992,
            "text_translation": ""
        },
        {
            "id": 1413039522758070277,
            "text": "RT  when jibeoms name appeared as one of bomins friends in LG Wing CF  yes bobeom together forever uB7zdpl",
            "created_at": "2021-07-08 07:37:29",
            "retweet_count": 56,
            "favorite_count": 0,
            "lang": "en",
            "geo": null,
            "coordinates": null,
            "mention": [],
            "label": "",
            "user_id": 1265945023855509504,
            "text_translation": ""
        },
        {
            "id": 1413033849529851907,
            "text": "RT  when jibeoms name appeared as one of bomins friends in LG Wing CF  yes bobeom together forever uB7zdpl",
            "created_at": "2021-07-08 07:14:57",
            "retweet_count": 56,
            "favorite_count": 0,
            "lang": "en",
            "geo": null,
            "coordinates": null,
            "mention": [],
            "label": "",
            "user_id": 819533074119553024,
            "text_translation": ""
        },
        {
            "id": 1413021591680679937,
            "text": "RT  when jibeoms name appeared as one of bomins friends in LG Wing CF  yes bobeom together forever uB7zdpl",
            "created_at": "2021-07-08 06:26:14",
            "retweet_count": 56,
            "favorite_count": 0,
            "lang": "en",
            "geo": null,
            "coordinates": null,
            "mention": [],
            "label": "",
            "user_id": 153731269,
            "text_translation": ""
        },
        {
            "id": 1413019704810119172,
            "text": "RT  when jibeoms name appeared as one of bomins friends in LG Wing CF  yes bobeom together forever uB7zdpl",
            "created_at": "2021-07-08 06:18:44",
            "retweet_count": 56,
            "favorite_count": 0,
            "lang": "en",
            "geo": null,
            "coordinates": null,
            "mention": [],
            "label": "",
            "user_id": 1183964813082284033,
            "text_translation": ""
        },
        {
            "id": 1413018828959752195,
            "text": "RT  when jibeoms name appeared as one of bomins friends in LG Wing CF  yes bobeom together forever uB7zdpl",
            "created_at": "2021-07-08 06:15:16",
            "retweet_count": 56,
            "favorite_count": 0,
            "lang": "en",
            "geo": null,
            "coordinates": null,
            "mention": [],
            "label": "",
            "user_id": 255964342,
            "text_translation": ""
        },
        {
            "id": 1413018530098794498,
            "text": "RT  when jibeoms name appeared as one of bomins friends in LG Wing CF  yes bobeom together forever uB7zdpl",
            "created_at": "2021-07-08 06:14:04",
            "retweet_count": 56,
            "favorite_count": 0,
            "lang": "en",
            "geo": null,
            "coordinates": null,
            "mention": [],
            "label": "",
            "user_id": 3286383115,
            "text_translation": ""
        },
        {
            "id": 1413015855508635648,
            "text": "RT  when jibeoms name appeared as one of bomins friends in LG Wing CF  yes bobeom together forever uB7zdpl",
            "created_at": "2021-07-08 06:03:27",
            "retweet_count": 56,
            "favorite_count": 0,
            "lang": "en",
            "geo": null,
            "coordinates": null,
            "mention": [],
            "label": "",
            "user_id": 1061147502576046080,
            "text_translation": ""
        },
        {
            "id": 1413010825850220546,
            "text": "RT  when jibeoms name appeared as one of bomins friends in LG Wing CF  yes bobeom together forever uB7zdpl",
            "created_at": "2021-07-08 05:43:28",
            "retweet_count": 56,
            "favorite_count": 0,
            "lang": "en",
            "geo": null,
            "coordinates": null,
            "mention": [],
            "label": "",
            "user_id": 1104243454526218242,
            "text_translation": ""
        },
        {
            "id": 1413009173239930884,
            "text": "RT  when jibeoms name appeared as one of bomins friends in LG Wing CF  yes bobeom together forever uB7zdpl",
            "created_at": "2021-07-08 05:36:53",
            "retweet_count": 56,
            "favorite_count": 0,
            "lang": "en",
            "geo": null,
            "coordinates": null,
            "mention": [],
            "label": "",
            "user_id": 1358452698090143744,
            "text_translation": ""
        },
        {
            "id": 1413008489480286208,
            "text": "RT  when jibeoms name appeared as one of bomins friends in LG Wing CF  yes bobeom together forever uB7zdpl",
            "created_at": "2021-07-08 05:34:10",
            "retweet_count": 56,
            "favorite_count": 0,
            "lang": "en",
            "geo": null,
            "coordinates": null,
            "mention": [],
            "label": "",
            "user_id": 1356207028918579201,
            "text_translation": ""
        },
        {
            "id": 1413005299766546435,
            "text": "RT  when jibeoms name appeared as one of bomins friends in LG Wing CF  yes bobeom together forever uB7zdpl",
            "created_at": "2021-07-08 05:21:30",
            "retweet_count": 56,
            "favorite_count": 0,
            "lang": "en",
            "geo": null,
            "coordinates": null,
            "mention": [],
            "label": "",
            "user_id": 1277859202002612224,
            "text_translation": ""
        },
        {
            "id": 1413003438770692097,
            "text": "RT  when jibeoms name appeared as one of bomins friends in LG Wing CF  yes bobeom together forever uB7zdpl",
            "created_at": "2021-07-08 05:14:06",
            "retweet_count": 56,
            "favorite_count": 0,
            "lang": "en",
            "geo": null,
            "coordinates": null,
            "mention": [],
            "label": "",
            "user_id": 1387278396317523974,
            "text_translation": ""
        },
        {
            "id": 1413002853560459264,
            "text": "RT  when jibeoms name appeared as one of bomins friends in LG Wing CF  yes bobeom together forever uB7zdpl",
            "created_at": "2021-07-08 05:11:47",
            "retweet_count": 56,
            "favorite_count": 0,
            "lang": "en",
            "geo": null,
            "coordinates": null,
            "mention": [],
            "label": "",
            "user_id": 782960638813364224,
            "text_translation": ""
        },
        {
            "id": 1413001998400561156,
            "text": "RT  when jibeoms name appeared as one of bomins friends in LG Wing CF  yes bobeom together forever uB7zdpl",
            "created_at": "2021-07-08 05:08:23",
            "retweet_count": 56,
            "favorite_count": 0,
            "lang": "en",
            "geo": null,
            "coordinates": null,
            "mention": [],
            "label": "",
            "user_id": 1193193518522486786,
            "text_translation": ""
        },
        {
            "id": 1413000276005457921,
            "text": "RT  when jibeoms name appeared as one of bomins friends in LG Wing CF  yes bobeom together forever uB7zdpl",
            "created_at": "2021-07-08 05:01:32",
            "retweet_count": 56,
            "favorite_count": 0,
            "lang": "en",
            "geo": null,
            "coordinates": null,
            "mention": [],
            "label": "",
            "user_id": 1263512566971523073,
            "text_translation": ""
        },
        {
            "id": 1412999434884034560,
            "text": "RT  when jibeoms name appeared as one of bomins friends in LG Wing CF  yes bobeom together forever uB7zdpl",
            "created_at": "2021-07-08 04:58:12",
            "retweet_count": 56,
            "favorite_count": 0,
            "lang": "en",
            "geo": null,
            "coordinates": null,
            "mention": [],
            "label": "",
            "user_id": 899389352500973568,
            "text_translation": ""
        },
        {
            "id": 1412992379947151366,
            "text": "RT  when jibeoms name appeared as one of bomins friends in LG Wing CF  yes bobeom together forever uB7zdpl",
            "created_at": "2021-07-08 04:30:10",
            "retweet_count": 56,
            "favorite_count": 0,
            "lang": "en",
            "geo": null,
            "coordinates": null,
            "mention": [],
            "label": "",
            "user_id": 1046378138136018945,
            "text_translation": ""
        },
        {
            "id": 1412991506625880065,
            "text": "RT  when jibeoms name appeared as one of bomins friends in LG Wing CF  yes bobeom together forever uB7zdpl",
            "created_at": "2021-07-08 04:26:41",
            "retweet_count": 56,
            "favorite_count": 0,
            "lang": "en",
            "geo": null,
            "coordinates": null,
            "mention": [],
            "label": "",
            "user_id": 1268352606260170753,
            "text_translation": ""
        },
        {
            "id": 1412991222306639874,
            "text": "RT  when jibeoms name appeared as one of bomins friends in LG Wing CF  yes bobeom together forever uB7zdpl",
            "created_at": "2021-07-08 04:25:34",
            "retweet_count": 56,
            "favorite_count": 0,
            "lang": "en",
            "geo": null,
            "coordinates": null,
            "mention": [],
            "label": "",
            "user_id": 876124997357494273,
            "text_translation": ""
        },
        {
            "id": 1412989327294951425,
            "text": "RT  when jibeoms name appeared as one of bomins friends in LG Wing CF  yes bobeom together forever uB7zdpl",
            "created_at": "2021-07-08 04:18:02",
            "retweet_count": 56,
            "favorite_count": 0,
            "lang": "en",
            "geo": null,
            "coordinates": null,
            "mention": [],
            "label": "",
            "user_id": 2657715962,
            "text_translation": ""
        },
        {
            "id": 1412987931401150464,
            "text": "RT  when jibeoms name appeared as one of bomins friends in LG Wing CF  yes bobeom together forever uB7zdpl",
            "created_at": "2021-07-08 04:12:29",
            "retweet_count": 56,
            "favorite_count": 0,
            "lang": "en",
            "geo": null,
            "coordinates": null,
            "mention": [],
            "label": "",
            "user_id": 1314350936282730496,
            "text_translation": ""
        },
        {
            "id": 1412986684451418113,
            "text": "RT  when jibeoms name appeared as one of bomins friends in LG Wing CF  yes bobeom together forever uB7zdpl",
            "created_at": "2021-07-08 04:07:32",
            "retweet_count": 56,
            "favorite_count": 0,
            "lang": "en",
            "geo": null,
            "coordinates": null,
            "mention": [],
            "label": "",
            "user_id": 455120090,
            "text_translation": ""
        },
        {
            "id": 1412986414598287365,
            "text": "RT  when jibeoms name appeared as one of bomins friends in LG Wing CF  yes bobeom together forever uB7zdpl",
            "created_at": "2021-07-08 04:06:27",
            "retweet_count": 56,
            "favorite_count": 0,
            "lang": "en",
            "geo": null,
            "coordinates": null,
            "mention": [],
            "label": "",
            "user_id": 1255875148466597894,
            "text_translation": ""
        },
        {
            "id": 1412985796424962055,
            "text": "RT  when jibeoms name appeared as one of bomins friends in LG Wing CF  yes bobeom together forever uB7zdpl",
            "created_at": "2021-07-08 04:04:00",
            "retweet_count": 56,
            "favorite_count": 0,
            "lang": "en",
            "geo": null,
            "coordinates": null,
            "mention": [],
            "label": "",
            "user_id": 1266697496287260672,
            "text_translation": ""
        },
        {
            "id": 1412980686055641088,
            "text": "RT  when jibeoms name appeared as one of bomins friends in LG Wing CF  yes bobeom together forever uB7zdpl",
            "created_at": "2021-07-08 03:43:42",
            "retweet_count": 56,
            "favorite_count": 0,
            "lang": "en",
            "geo": null,
            "coordinates": null,
            "mention": [],
            "label": "",
            "user_id": 65341363,
            "text_translation": ""
        },
        {
            "id": 1412979729070759945,
            "text": "RT  when jibeoms name appeared as one of bomins friends in LG Wing CF  yes bobeom together forever uB7zdpl",
            "created_at": "2021-07-08 03:39:53",
            "retweet_count": 56,
            "favorite_count": 0,
            "lang": "en",
            "geo": null,
            "coordinates": null,
            "mention": [],
            "label": "",
            "user_id": 150857454,
            "text_translation": ""
        },
        {
            "id": 1412979641468522497,
            "text": "RT  when jibeoms name appeared as one of bomins friends in LG Wing CF  yes bobeom together forever uB7zdpl",
            "created_at": "2021-07-08 03:39:33",
            "retweet_count": 56,
            "favorite_count": 0,
            "lang": "en",
            "geo": null,
            "coordinates": null,
            "mention": [],
            "label": "",
            "user_id": 1347755436586491907,
            "text_translation": ""
        },
        {
            "id": 1412979527412641803,
            "text": "RT  when jibeoms name appeared as one of bomins friends in LG Wing CF  yes bobeom together forever uB7zdpl",
            "created_at": "2021-07-08 03:39:05",
            "retweet_count": 56,
            "favorite_count": 0,
            "lang": "en",
            "geo": null,
            "coordinates": null,
            "mention": [],
            "label": "",
            "user_id": 810852424164450304,
            "text_translation": ""
        },
        {
            "id": 1412972594744021005,
            "text": "RT  when jibeoms name appeared as one of bomins friends in LG Wing CF  yes bobeom together forever uB7zdpl",
            "created_at": "2021-07-08 03:11:33",
            "retweet_count": 56,
            "favorite_count": 0,
            "lang": "en",
            "geo": null,
            "coordinates": null,
            "mention": [],
            "label": "",
            "user_id": 900299328362659840,
            "text_translation": ""
        },
        {
            "id": 1412972007617032200,
            "text": "RT  when jibeoms name appeared as one of bomins friends in LG Wing CF  yes bobeom together forever uB7zdpl",
            "created_at": "2021-07-08 03:09:13",
            "retweet_count": 56,
            "favorite_count": 0,
            "lang": "en",
            "geo": null,
            "coordinates": null,
            "mention": [],
            "label": "",
            "user_id": 129765293,
            "text_translation": ""
        },
        {
            "id": 1412971645015187459,
            "text": "RT  when jibeoms name appeared as one of bomins friends in LG Wing CF  yes bobeom together forever uB7zdpl",
            "created_at": "2021-07-08 03:07:46",
            "retweet_count": 56,
            "favorite_count": 0,
            "lang": "en",
            "geo": null,
            "coordinates": null,
            "mention": [],
            "label": "",
            "user_id": 1364816050580201472,
            "text_translation": ""
        },
        {
            "id": 1412971123738697728,
            "text": "RT  when jibeoms name appeared as one of bomins friends in LG Wing CF  yes bobeom together forever uB7zdpl",
            "created_at": "2021-07-08 03:05:42",
            "retweet_count": 56,
            "favorite_count": 0,
            "lang": "en",
            "geo": null,
            "coordinates": null,
            "mention": [],
            "label": "",
            "user_id": 1255892905396367360,
            "text_translation": ""
        },
        {
            "id": 1412970950652399616,
            "text": "RT  when jibeoms name appeared as one of bomins friends in LG Wing CF  yes bobeom together forever uB7zdpl",
            "created_at": "2021-07-08 03:05:01",
            "retweet_count": 56,
            "favorite_count": 0,
            "lang": "en",
            "geo": null,
            "coordinates": null,
            "mention": [],
            "label": "",
            "user_id": 1322523303529996289,
            "text_translation": ""
        },
        {
            "id": 1412970261318602759,
            "text": "RT  when jibeoms name appeared as one of bomins friends in LG Wing CF  yes bobeom together forever uB7zdpl",
            "created_at": "2021-07-08 03:02:16",
            "retweet_count": 56,
            "favorite_count": 0,
            "lang": "en",
            "geo": null,
            "coordinates": null,
            "mention": [],
            "label": "",
            "user_id": 1222199173858185217,
            "text_translation": ""
        },
        {
            "id": 1412970127776047106,
            "text": "RT  when jibeoms name appeared as one of bomins friends in LG Wing CF  yes bobeom together forever uB7zdpl",
            "created_at": "2021-07-08 03:01:44",
            "retweet_count": 56,
            "favorite_count": 0,
            "lang": "en",
            "geo": null,
            "coordinates": null,
            "mention": [],
            "label": "",
            "user_id": 1014487065134678016,
            "text_translation": ""
        },
        {
            "id": 1412969730990743557,
            "text": "RT  when jibeoms name appeared as one of bomins friends in LG Wing CF  yes bobeom together forever uB7zdpl",
            "created_at": "2021-07-08 03:00:10",
            "retweet_count": 56,
            "favorite_count": 0,
            "lang": "en",
            "geo": null,
            "coordinates": null,
            "mention": [],
            "label": "",
            "user_id": 1190198327280668672,
            "text_translation": ""
        },
        {
            "id": 1412969646530072579,
            "text": "RT  when jibeoms name appeared as one of bomins friends in LG Wing CF  yes bobeom together forever uB7zdpl",
            "created_at": "2021-07-08 02:59:50",
            "retweet_count": 56,
            "favorite_count": 0,
            "lang": "en",
            "geo": null,
            "coordinates": null,
            "mention": [],
            "label": "",
            "user_id": 912304121197215744,
            "text_translation": ""
        },
        {
            "id": 1412967055058345985,
            "text": "when jibeoms name appeared as one of bomins friends in LG Wing CF  yes bobeom together forever WKs1cJ1GB8",
            "created_at": "2021-07-08 02:49:32",
            "retweet_count": 56,
            "favorite_count": 163,
            "lang": "en",
            "geo": null,
            "coordinates": null,
            "mention": [],
            "label": "",
            "user_id": 1379944815740121090,
            "text_translation": ""
        },
        {
            "id": 1412925001280327689,
            "text": "The NorthlinesLG launches Web Portal of Electrical Inspection Wing  Northlines  NISsfZXvXv CEARLBxNHp",
            "created_at": "2021-07-08 00:02:25",
            "retweet_count": 0,
            "favorite_count": 0,
            "lang": "en",
            "geo": null,
            "coordinates": null,
            "mention": [
                "Web"
            ],
            "label": "",
            "user_id": 1286099343645249537,
            "text_translation": ""
        }
    ]
}